odoo9_addon_account_analytic_distribution-9.0.1.0.0.99.dev7-py2.7-nspkg.pth
odoo9_addon_account_analytic_distribution-9.0.1.0.0.99.dev7.dist-info/METADATA
odoo9_addon_account_analytic_distribution-9.0.1.0.0.99.dev7.dist-info/RECORD
odoo9_addon_account_analytic_distribution-9.0.1.0.0.99.dev7.dist-info/WHEEL
odoo9_addon_account_analytic_distribution-9.0.1.0.0.99.dev7.dist-info/namespace_packages.txt
odoo9_addon_account_analytic_distribution-9.0.1.0.0.99.dev7.dist-info/top_level.txt
odoo_addons/account_analytic_distribution/README.rst
odoo_addons/account_analytic_distribution/__init__.py
odoo_addons/account_analytic_distribution/__openerp__.py
odoo_addons/account_analytic_distribution/i18n/account_analytic_distribution.pot
odoo_addons/account_analytic_distribution/i18n/ca.po
odoo_addons/account_analytic_distribution/i18n/es.po
odoo_addons/account_analytic_distribution/migrations/9.0.1.0.0/pre-migration.py
odoo_addons/account_analytic_distribution/models/__init__.py
odoo_addons/account_analytic_distribution/models/account_analytic_distribution.py
odoo_addons/account_analytic_distribution/models/account_invoice.py
odoo_addons/account_analytic_distribution/models/account_invoice_line.py
odoo_addons/account_analytic_distribution/models/account_move_line.py
odoo_addons/account_analytic_distribution/models/res_company.py
odoo_addons/account_analytic_distribution/security/ir.model.access.csv
odoo_addons/account_analytic_distribution/static/description/icon.png
odoo_addons/account_analytic_distribution/tests/__init__.py
odoo_addons/account_analytic_distribution/tests/test_analytic_distribution.py
odoo_addons/account_analytic_distribution/views/account_analytic_distribution_view.xml
odoo_addons/account_analytic_distribution/views/account_invoice_view.xml
odoo_addons/account_analytic_distribution/views/account_move_line_view.xml
odoo_addons/account_analytic_distribution/views/account_move_view.xml
odoo_addons/account_analytic_distribution/views/company_view.xml
